biblary/__init__.py
biblary/forms.py
biblary/settings.py
biblary/urls.py
biblary/utils.py
biblary/views.py
biblary/bibliography/__init__.py
biblary/bibliography/bibliography.py
biblary/bibliography/entry.py
biblary/bibliography/exceptions.py
biblary/bibliography/adapter/__init__.py
biblary/bibliography/adapter/abstract.py
biblary/bibliography/adapter/bibtex.py
biblary/bibliography/storage/__init__.py
biblary/bibliography/storage/abstract.py
biblary/bibliography/storage/file_system.py
biblary/templates/biblary/index.html
biblary/templates/biblary/upload_entry.html
biblary/templates/biblary/upload_file.html
biblary/templatetags/__init__.py
biblary/templatetags/authors.py
biblary-0.2.0.dist-info/LICENSE.txt
biblary-0.2.0.dist-info/WHEEL
biblary-0.2.0.dist-info/METADATA
biblary-0.2.0.dist-info/RECORD
