Metadata-Version: 2.1
Name: biblary
Version: 0.2.0
Summary: A Django application to provide a bibliography based on a bibtex library.
Keywords: bibliography,django,bibtex
Author-email: "Sebastiaan P. Huber" <mail@sphuber.net>
Requires-Python: >=3.7
Classifier: Development Status :: 4 - Beta
Classifier: Framework :: Django
Classifier: License :: OSI Approved :: MIT License
Classifier: Operating System :: POSIX :: Linux
Classifier: Programming Language :: Python
Classifier: Programming Language :: Python :: 3.7
Classifier: Programming Language :: Python :: 3.8
Classifier: Programming Language :: Python :: 3.9
Classifier: Programming Language :: Python :: 3.10
Requires-Dist: bibtexparser
Requires-Dist: django >= 3.0
Requires-Dist: typing-extensions;python_version < "3.8"
Requires-Dist: pre-commit ; extra == "dev"
Requires-Dist: pylint ; extra == "dev"
Requires-Dist: pytest ; extra == "dev"
Requires-Dist: pytest-django ; extra == "dev"
Project-URL: Source, https://github.com/sphuber/biblary
Provides-Extra: dev
